azureml/__init__.py
azureml/pipeline/__init__.py
azureml/pipeline/wrapper/__init__.py
azureml/pipeline/wrapper/_dataset.py
azureml/pipeline/wrapper/_graph_to_code.py
azureml/pipeline/wrapper/_mock_parallel_driver.py
azureml/pipeline/wrapper/_module_dto.py
azureml/pipeline/wrapper/_module_run_helper.py
azureml/pipeline/wrapper/_pipeline_parameters.py
azureml/pipeline/wrapper/_pipeline_run_orchestrator.py
azureml/pipeline/wrapper/_published_pipeline.py
azureml/pipeline/wrapper/_utils.py
azureml/pipeline/wrapper/module.py
azureml/pipeline/wrapper/pipeline.py
azureml/pipeline/wrapper/pipeline_endpoint.py
azureml/pipeline/wrapper/pipeline_run.py
azureml/pipeline/wrapper/_cli/__init__.py
azureml/pipeline/wrapper/_cli/module_commands.py
azureml/pipeline/wrapper/_cli/module_subgroup.py
azureml/pipeline/wrapper/_restclients/__init__.py
azureml/pipeline/wrapper/_restclients/service_caller.py
azureml/pipeline/wrapper/_restclients/service_caller_factory.py
azureml/pipeline/wrapper/debug/__init__.py
azureml/pipeline/wrapper/debug/_constants.py
azureml/pipeline/wrapper/dsl/__init__.py
azureml/pipeline/wrapper/dsl/_utils.py
azureml/pipeline/wrapper/dsl/_version.py
azureml/pipeline/wrapper/dsl/module.py
azureml_pipeline_wrapper-0.9.18.post2.dist-info/LICENSE.txt
azureml_pipeline_wrapper-0.9.18.post2.dist-info/METADATA
azureml_pipeline_wrapper-0.9.18.post2.dist-info/WHEEL
azureml_pipeline_wrapper-0.9.18.post2.dist-info/entry_points.txt
azureml_pipeline_wrapper-0.9.18.post2.dist-info/top_level.txt
azureml_pipeline_wrapper-0.9.18.post2.dist-info/RECORD
